[
  {
    "title": "EV Battery Life India: What Buyers Should Know Before Choosing an Electric Car",
    "url": "https://comeback2000.github.io/Car-news/posts/ev-battery-life-india.html",
    "facebookPostId": "176747645744060_872138815916294",
    "publishDate": "2026-06-04T07:27:58.338Z",
    "status": "published",
    "imageUrl": "https://comeback2000.github.io/Car-news/assets/ev-battery-life-india-thumbnail.jpg",
    "captionHash": "559956caa91d94aefe574237a7bafc805665e1d322ee37e2533ae1771d8c1810",
    "dryRun": false
  },
  {
    "title": "Cheap Electric Cars India: Best Value EV Choices Buyers Are Watching Now",
    "url": "https://comeback2000.github.io/Car-news/posts/cheap-electric-cars-india-2026.html",
    "facebookPostId": "176747645744060_872138715916304",
    "publishDate": "2026-06-04T07:27:51.247Z",
    "status": "published",
    "imageUrl": "https://comeback2000.github.io/Car-news/assets/cheap-electric-cars-india-2026-thumbnail.jpg",
    "captionHash": "4e356b0d04355b34553830982da9669a8272d5a9ea2b73f00b4d851132dfa17e",
    "dryRun": false
  },
  {
    "title": "Tata Curvv EV vs Creta EV: Which Electric SUV Makes More Sense?",
    "url": "https://comeback2000.github.io/Car-news/posts/tata-curvv-ev-vs-creta-ev.html",
    "facebookPostId": "176747645744060_872138635916312",
    "publishDate": "2026-06-04T07:27:44.092Z",
    "status": "published",
    "imageUrl": "https://comeback2000.github.io/Car-news/assets/tata-curvv-ev-vs-creta-ev-thumbnail.jpg",
    "captionHash": "9cb2d5df6567f112c73504cc566291bada08d981b51e8dc312605f727b68e87d",
    "dryRun": false
  },
  {
    "title": "Harrier EV vs XEV 9e: The Premium Electric SUV Fight Buyers Must Watch",
    "url": "https://comeback2000.github.io/Car-news/posts/harrier-ev-vs-xev-9e.html",
    "facebookPostId": "176747645744060_872138559249653",
    "publishDate": "2026-06-04T07:27:38.074Z",
    "status": "published",
    "imageUrl": "https://comeback2000.github.io/Car-news/assets/harrier-ev-vs-xev-9e-thumbnail.jpg",
    "captionHash": "18dcfba65f57469d46e5b10153b2b4d7916d63dc78bfac616e4357625aa1ac89",
    "dryRun": false
  },
  {
    "title": "EV Battery Life India: What Buyers Should Know Before Choosing an Electric Car",
    "url": "https://comeback2000.github.io/Car-news/posts/ev-battery-life-india.html",
    "facebookPostId": null,
    "publishDate": "2026-06-04T05:30:43.794Z",
    "status": "failed",
    "message": "Error validating access token: Session has expired on Wednesday, 03-Jun-26 09:00:00 PDT. The current time is Wednesday, 03-Jun-26 22:30:43 PDT. (code 190)"
  },
  {
    "title": "Cheap Electric Cars India: Best Value EV Choices Buyers Are Watching Now",
    "url": "https://comeback2000.github.io/Car-news/posts/cheap-electric-cars-india-2026.html",
    "facebookPostId": null,
    "publishDate": "2026-06-04T05:30:43.274Z",
    "status": "failed",
    "message": "Error validating access token: Session has expired on Wednesday, 03-Jun-26 09:00:00 PDT. The current time is Wednesday, 03-Jun-26 22:30:42 PDT. (code 190)"
  },
  {
    "title": "Tata Curvv EV vs Creta EV: Which Electric SUV Makes More Sense?",
    "url": "https://comeback2000.github.io/Car-news/posts/tata-curvv-ev-vs-creta-ev.html",
    "facebookPostId": null,
    "publishDate": "2026-06-04T05:30:42.852Z",
    "status": "failed",
    "message": "Error validating access token: Session has expired on Wednesday, 03-Jun-26 09:00:00 PDT. The current time is Wednesday, 03-Jun-26 22:30:42 PDT. (code 190)"
  },
  {
    "title": "Harrier EV vs XEV 9e: The Premium Electric SUV Fight Buyers Must Watch",
    "url": "https://comeback2000.github.io/Car-news/posts/harrier-ev-vs-xev-9e.html",
    "facebookPostId": null,
    "publishDate": "2026-06-04T05:30:42.407Z",
    "status": "failed",
    "message": "Error validating access token: Session has expired on Wednesday, 03-Jun-26 09:00:00 PDT. The current time is Wednesday, 03-Jun-26 22:30:41 PDT. (code 190)"
  },
  {
    "title": "Upcoming EV Cars India 2026: 7 Launches That Could Shake Up the Market",
    "url": "https://comeback2000.github.io/Car-news/posts/upcoming-ev-cars-india-2026-watchlist.html",
    "facebookPostId": "176747645744060_871527002644142",
    "publishDate": "2026-06-03T14:25:21.598Z",
    "status": "published",
    "imageUrl": "https://comeback2000.github.io/Car-news/assets/upcoming-ev-cars-india-thumbnail.jpg",
    "captionHash": "f5d8e2965a8f2f64fd8fbb598bbfb601ae22174660ad4699ad135bdedc29d91a",
    "dryRun": false
  },
  {
    "title": "Upcoming EV Cars India 2026: 7 Launches That Could Shake Up the Market",
    "url": "https://comeback2000.github.io/Car-news/posts/upcoming-ev-cars-india-2026-watchlist.html",
    "facebookPostId": null,
    "publishDate": "2026-06-03T14:24:48.906Z",
    "status": "failed",
    "message": "(#200) The permission(s) publish_actions are not available. It has been deprecated. If you want to provide a way for your app users to share content to Facebook, we encourage you to use our Sharing products instead. (code 200)"
  }
]
